wec/__init__.py
wec/cli.py
wec/wx.py
wec-0.1.0.dist-info/licenses/LICENSE
wec-0.1.0.dist-info/METADATA
wec-0.1.0.dist-info/WHEEL
wec-0.1.0.dist-info/top_level.txt
wec-0.1.0.dist-info/RECORD
