Metadata-Version: 2.4
Name: wec
Version: 0.1.0
Summary: WeatherEye Controller
Author-email: Ian Edwards <ian@myacorn.com>
License: MIT
Classifier: Programming Language :: Python :: 3
Classifier: License :: OSI Approved :: MIT License
Classifier: Operating System :: OS Independent
Requires-Python: >=3.8
License-File: LICENSE
Dynamic: license-file
